<annotation>
	<folder>train</folder>
	<filename>IMG_2870.JPG</filename>
	<path>D:\MSPR_AR\xml_to_csv\images\train\IMG_2870.JPG</path>
	<source>
		<database>Unknown</database>
	</source>
	<size>
		<width>4032</width>
		<height>3024</height>
		<depth>3</depth>
	</size>
	<segmented>0</segmented>
	<object>
		<name>Singe</name>
		<pose>Unspecified</pose>
		<truncated>0</truncated>
		<difficult>0</difficult>
		<bndbox>
			<xmin>2363</xmin>
			<ymin>1259</ymin>
			<xmax>2724</xmax>
			<ymax>2364</ymax>
		</bndbox>
	</object>
</annotation>
